[
    {
        "name": "Мерзкая опухоль",
        "description": "Неуправляемо растущая опухоль на теле жертвы, состоящая из тут же возникающих жира, хрящей и вкраплений зубов.",
        "runes": "Ч И Черной Магии,Ч Р Хаоса+,В Р Роста"        
    },
    {
        "name": "Сильное исцеление",
        "runes": "Б И Белой Магии,Б Р Исцеления+,Б Р Исцеления,Б Р Исцеления"
    },
    {
        "name": "Заклятие кошмарной гибели",
        "description": "Кошмарная моментальная гибель.",
        "runes": "Ч И Смерти,Ч Р Несчастья+,С И Силы"
    },
    {
        "name": "Заклятие деликатного сокрытия магии",
        "description": "Накладывается строго по поверхности, скрывает присутствие магии группы целей.",
        "runes": "В И Единства,В И Внимания,В Р Притока+,В Р Фокуса"
    }
]